sherlock/__init__.py
sherlock/_modidx.py
sherlock/auth.py
sherlock/config.py
sherlock/core.py
sherlock/crypto.py
sherlock_domains-0.1.7.dist-info/licenses/LICENSE
sherlock_domains-0.1.7.dist-info/METADATA
sherlock_domains-0.1.7.dist-info/WHEEL
sherlock_domains-0.1.7.dist-info/entry_points.txt
sherlock_domains-0.1.7.dist-info/top_level.txt
sherlock_domains-0.1.7.dist-info/RECORD
