Metadata-Version: 2.4
Name: sherlock-domains
Version: 0.1.7
Summary: Sherlock Domains Agentic SDK for python
Home-page: https://github.com/fewsats/sherlock-python
Author: Jordi Montes, Pol Alvarez
Author-email: jordi@fewsats.com, pol@fewsats.com
License: Apache Software License 2.0
Keywords: nbdev jupyter notebook python ai-agents llm domains agentic
Classifier: Development Status :: 4 - Beta
Classifier: Intended Audience :: Developers
Classifier: Natural Language :: English
Classifier: Programming Language :: Python :: 3.7
Classifier: Programming Language :: Python :: 3.8
Classifier: Programming Language :: Python :: 3.9
Classifier: Programming Language :: Python :: 3.10
Classifier: Programming Language :: Python :: 3.11
Classifier: Programming Language :: Python :: 3.12
Classifier: License :: OSI Approved :: Apache Software License
Requires-Python: >=3.7
License-File: LICENSE
Requires-Dist: fastcore>=1.7.28
Requires-Dist: httpx
Requires-Dist: cryptography
Provides-Extra: dev
Requires-Dist: nbdev; extra == "dev"
Requires-Dist: claudette; extra == "dev"
Requires-Dist: fewsats; extra == "dev"
Requires-Dist: twine; extra == "dev"
Requires-Dist: python-dotenv; extra == "dev"
Requires-Dist: streamlit; extra == "dev"
Dynamic: author
Dynamic: author-email
Dynamic: classifier
Dynamic: description
Dynamic: description-content-type
Dynamic: home-page
Dynamic: keywords
Dynamic: license
Dynamic: license-file
Dynamic: provides-extra
Dynamic: requires-dist
Dynamic: requires-python
Dynamic: summary
